GEFormer/_init_.py
geformerv1_0-1.1.2.dist-info/METADATA
geformerv1_0-1.1.2.dist-info/WHEEL
geformerv1_0-1.1.2.dist-info/top_level.txt
geformerv1_0-1.1.2.dist-info/RECORD
