Metadata-Version: 2.4
Name: GEFormerV1.0
Version: 1.1.2
Summary: Meta-package that installs all dependencies for YourModel
Home-page: https://github.com/Deep-Breeding/GEFormer
Author: yz
Author-email: wgs2038@163.com
Classifier: Programming Language :: Python :: 3
Classifier: License :: OSI Approved :: MIT License
Classifier: Operating System :: OS Independent
Requires-Python: >=3.8
Requires-Dist: alembic==1.14.1
Requires-Dist: blinker==1.8.2
Requires-Dist: Brotli==1.1.0
Requires-Dist: captum==0.7.0
Requires-Dist: click==8.1.8
Requires-Dist: cloudpickle==3.1.1
Requires-Dist: colorlog==6.9.0
Requires-Dist: contourpy==1.1.1
Requires-Dist: cycler==0.12.1
Requires-Dist: einops==0.8.0
Requires-Dist: filelock==3.16.1
Requires-Dist: Flask==3.0.3
Requires-Dist: Flask-Compress==1.15
Requires-Dist: fonttools==4.56.0
Requires-Dist: fsspec==2025.2.0
Requires-Dist: greenlet==3.1.1
Requires-Dist: imageio==2.35.1
Requires-Dist: importlib_metadata==8.5.0
Requires-Dist: importlib_resources==6.4.5
Requires-Dist: itsdangerous==2.2.0
Requires-Dist: Jinja2==3.1.5
Requires-Dist: joblib==1.4.2
Requires-Dist: kiwisolver==1.4.7
Requires-Dist: lazy_loader==0.4
Requires-Dist: llvmlite==0.41.1
Requires-Dist: Mako==1.3.9
Requires-Dist: MarkupSafe==2.1.5
Requires-Dist: matplotlib==3.7.5
Requires-Dist: mpmath==1.3.0
Requires-Dist: networkx==3.1
Requires-Dist: numba==0.58.1
Requires-Dist: numpy==1.24.4
Requires-Dist: nvidia-cublas-cu12==12.1.3.1
Requires-Dist: nvidia-cuda-cupti-cu12==12.1.105
Requires-Dist: nvidia-cuda-nvrtc-cu12==12.1.105
Requires-Dist: nvidia-cuda-runtime-cu12==12.1.105
Requires-Dist: nvidia-cudnn-cu12==9.1.0.70
Requires-Dist: nvidia-cufft-cu12==11.0.2.54
Requires-Dist: nvidia-curand-cu12==10.3.2.106
Requires-Dist: nvidia-cusolver-cu12==11.4.5.107
Requires-Dist: nvidia-cusparse-cu12==12.1.0.106
Requires-Dist: nvidia-nccl-cu12==2.20.5
Requires-Dist: nvidia-nvjitlink-cu12==12.8.61
Requires-Dist: nvidia-nvtx-cu12==12.1.105
Requires-Dist: optuna==4.2.0
Requires-Dist: packaging==24.2
Requires-Dist: pandas==2.0.3
Requires-Dist: pillow==10.4.0
Requires-Dist: pyparsing==3.1.4
Requires-Dist: python-dateutil==2.9.0.post0
Requires-Dist: pytz==2025.1
Requires-Dist: PyWavelets==1.4.1
Requires-Dist: PyYAML==6.0.2
Requires-Dist: saliency==0.2.1
Requires-Dist: scikit-image==0.21.0
Requires-Dist: scikit-learn==1.3.2
Requires-Dist: scipy==1.10.1
Requires-Dist: seaborn==0.13.2
Requires-Dist: six==1.17.0
Requires-Dist: slicer==0.0.7
Requires-Dist: SQLAlchemy==2.0.38
Requires-Dist: sympy==1.13.3
Requires-Dist: threadpoolctl==3.5.0
Requires-Dist: tifffile==2023.7.10
Requires-Dist: torch==2.4.1
Requires-Dist: tqdm==4.67.1
Requires-Dist: triton==3.0.0
Requires-Dist: typing_extensions==4.12.2
Requires-Dist: tzdata==2025.1
Requires-Dist: Werkzeug==3.0.6
Requires-Dist: zipp==3.20.2
Requires-Dist: zstandard==0.23.0
Dynamic: author
Dynamic: author-email
Dynamic: classifier
Dynamic: description-content-type
Dynamic: home-page
Dynamic: requires-dist
Dynamic: requires-python
Dynamic: summary
